pandas_video_methods/__init__.py
pandas_video_methods/core.py
pandas_video_methods/dask.py
pandas_video_methods/huggingface.py
pandas_video_methods-0.0.1.dist-info/LICENSE
pandas_video_methods-0.0.1.dist-info/METADATA
pandas_video_methods-0.0.1.dist-info/WHEEL
pandas_video_methods-0.0.1.dist-info/RECORD
