Metadata-Version: 2.3
Name: pandas-video-methods
Version: 0.0.1
Summary: Video methods for pandas dataframes using TorchCodec
License: Apache-2.0
Author: Quentin Lhoest
Requires-Python: >=3.10
Classifier: License :: OSI Approved :: Apache Software License
Classifier: Programming Language :: Python :: 3
Classifier: Programming Language :: Python :: 3.10
Classifier: Programming Language :: Python :: 3.11
Classifier: Programming Language :: Python :: 3.12
Classifier: Programming Language :: Python :: 3.13
Requires-Dist: numpy (>=2.0)
Requires-Dist: pandas (>=2.0)
Requires-Dist: pyarrow (>=0.18)
Requires-Dist: torchcodec (>=0.7)
